django_crystal_small
