Metadata-Version: 1.0
Name: django-crystal-small
Version: 2011.10.20
Summary: Everaldo's Crystal icons (small sizes) bundled for direct consumption from Django applications
Home-page: http://www.everaldo.com/crystal/
Author: Everaldo Coehlo, Lukasz Langa
Author-email: contact@everaldo.com, lukasz@langa.pl
License: LGPL
Keywords: django small crystal icons everaldo lgpl static
Platform: any
Classifier: Development Status :: 6 - Mature
Classifier: Framework :: Django
Classifier: Intended Audience :: Developers
Classifier: License :: OSI Approved :: GNU Library or Lesser General Public License (LGPL)
Classifier: Natural Language :: English
Classifier: Operating System :: OS Independent
Classifier: Programming Language :: Python
Classifier: Programming Language :: Python :: 2.5
Classifier: Programming Language :: Python :: 2.6
Classifier: Programming Language :: Python :: 2.7
Classifier: Topic :: Internet :: WWW/HTTP
Classifier: Topic :: Multimedia :: Graphics
Classifier: Topic :: Software Development :: Libraries :: Python Modules
